strats_oanda/__init__.py
strats_oanda/config.py
strats_oanda/logger.py
strats_oanda/py.typed
strats_oanda/client/__init__.py
strats_oanda/client/instrument.py
strats_oanda/client/order.py
strats_oanda/client/pricing.py
strats_oanda/client/transaction.py
strats_oanda/converter/__init__.py
strats_oanda/converter/pricing.py
strats_oanda/helper/__init__.py
strats_oanda/helper/datetime.py
strats_oanda/helper/json.py
strats_oanda/model/__init__.py
strats_oanda/model/common.py
strats_oanda/model/instrument.py
strats_oanda/model/order.py
strats_oanda/model/pricing.py
strats_oanda/model/transaction.py
strats_oanda/state/__init__.py
strats_oanda/state/trade/__init__.py
strats_oanda/state/trade/metrics.py
strats_oanda/state/trade/trade.py
strats_oanda-0.1.6.dist-info/METADATA
strats_oanda-0.1.6.dist-info/WHEEL
strats_oanda-0.1.6.dist-info/RECORD
